COPYING
MANIFEST.in
README.rst
setup.py
cmsplugin_footnote/__init__.py
cmsplugin_footnote/cms_plugins.py
cmsplugin_footnote/models.py
cmsplugin_footnote/settings.py
cmsplugin_footnote/utils.py
cmsplugin_footnote.egg-info/PKG-INFO
cmsplugin_footnote.egg-info/SOURCES.txt
cmsplugin_footnote.egg-info/dependency_links.txt
cmsplugin_footnote.egg-info/not-zip-safe
cmsplugin_footnote.egg-info/requires.txt
cmsplugin_footnote.egg-info/top_level.txt
cmsplugin_footnote/locale/de/LC_MESSAGES/django.mo
cmsplugin_footnote/locale/de/LC_MESSAGES/django.po
cmsplugin_footnote/locale/en/LC_MESSAGES/django.mo
cmsplugin_footnote/locale/en/LC_MESSAGES/django.po
cmsplugin_footnote/locale/es/LC_MESSAGES/django.mo
cmsplugin_footnote/locale/es/LC_MESSAGES/django.po
cmsplugin_footnote/locale/fr/LC_MESSAGES/django.mo
cmsplugin_footnote/locale/fr/LC_MESSAGES/django.po
cmsplugin_footnote/locale/it/LC_MESSAGES/django.mo
cmsplugin_footnote/locale/it/LC_MESSAGES/django.po
cmsplugin_footnote/locale/nl/LC_MESSAGES/django.mo
cmsplugin_footnote/locale/nl/LC_MESSAGES/django.po
cmsplugin_footnote/locale/pl/LC_MESSAGES/django.mo
cmsplugin_footnote/locale/pl/LC_MESSAGES/django.po
cmsplugin_footnote/locale/pt/LC_MESSAGES/django.mo
cmsplugin_footnote/locale/pt/LC_MESSAGES/django.po
cmsplugin_footnote/locale/ru/LC_MESSAGES/django.mo
cmsplugin_footnote/locale/ru/LC_MESSAGES/django.po
cmsplugin_footnote/locale/sl/LC_MESSAGES/django.mo
cmsplugin_footnote/locale/sl/LC_MESSAGES/django.po
cmsplugin_footnote/migrations/0001_initial.py
cmsplugin_footnote/migrations/__init__.py
cmsplugin_footnote/south_migrations/0001_initial.py
cmsplugin_footnote/south_migrations/__init__.py
cmsplugin_footnote/static/css/cmsplugin-footnote.css
cmsplugin_footnote/static/icons/footnote_symbol.png
cmsplugin_footnote/templates/cmsplugin_footnote/footnote_list.html
cmsplugin_footnote/templates/cmsplugin_footnote/footnote_symbol.html
cmsplugin_footnote/templatetags/__init__.py
cmsplugin_footnote/templatetags/footnote.py