Metadata-Version: 1.1
Name: cmsplugin-footnote
Version: 0.3.4
Summary: A simple plugin allowing to add footnotes in django CMS.
Home-page: https://github.com/BertrandBordage/cmsplugin-footnote
Author: Bertrand Bordage
Author-email: bordage.bertrand@gmail.com
License: BSD
Platform: UNKNOWN
Classifier: Development Status :: 3 - Alpha
Classifier: Framework :: Django
Classifier: Intended Audience :: Developers
Classifier: License :: OSI Approved :: BSD License
Classifier: Operating System :: OS Independent
Classifier: Programming Language :: Python
Classifier: Topic :: Internet :: WWW/HTTP
